Workbook

Sheet EP N°_
B6: Registro de ingresos y egresos | L6: Balance Ingresos v/s Egresos
B8: Contrato: | G8: EdP N.°: | L8: Contrato: | M8: =D8 -> 0
B9: N° Contrato: | G9: Periodo: | L9: N° Contrato: | M9: =D9 -> 0
L10: N.° EdP: | M10: =I8 -> 0
B11: N° | C11: Fecha | D11: Descripción | E11: Categoria | F11: Tipo | G11: Cant. | H11: Unidad | I11: Precio unitario | J11: Total | L11: Periodo: | M11: =I9 -> 0 | N11: =J9 -> 0
B12: 1 | J12: =I12*G12 -> 0
B13: 2 | J13: =I13*G13 -> 0 | L13: Total Ingresos | M13: Egresos | R13: Total Egresos | S13: Utilidad
B14: 3 | J14: =I14*G14 -> 0 | M14: MO | N14: M | O14: H | P14: EPP | Q14: GG
B15: 4 | J15: =I15*G15 -> 0 | L15: =SUMIF('EP N°_'!$F$12:$F$10011,"=Ingreso",'EP N°_'!$J$12:$J$10011) -> 0 | M15: =SUMIFS('EP N°_'!$J$12:$J$1011,'EP N°_'!$E$12:$E$1011,"=MO",'EP N°_'!$F$12:$F$1011,"=Egreso") -> 0 | N15: =SUMIFS('EP N°_'!$J$12:$J$1011,'EP N°_'!$E$12:$E$1011,"=M",'EP N°_'!$F$12:$F$1011,"=Egreso") -> 0 | O15: =SUMIFS('EP N°_'!$J$12:$J$1011,'EP N°_'!$E$12:$E$1011,"=H",'EP N°_'!$F$12:$F$1011,"=Egreso") -> 0 | P15: =SUMIFS('EP N°_'!$J$12:$J$1011,'EP N°_'!$E$12:$E$1011,"=EPP",'EP N°_'!$F$12:$F$1011,"=Egreso") -> 0 | Q15: =SUMIFS('EP N°_'!$J$12:$J$1011,'EP N°_'!$E$12:$E$1011,"=GG",'EP N°_'!$F$12:$F$1011,"=Egreso") -> 0 | R15: =SUM(M15:Q15) -> 0 | S15: =L15-R15 -> 0
B16: 5 | J16: =I16*G16 -> 0
B17: 6 | J17: =I17*G17 -> 0 | S17: Rentabilidad
B18: 7 | J18: =I18*G18 -> 0
B19: 8 | J19: =I19*G19 -> 0 | S19: =IF(ISERROR(S15/L15),"-",S15/L15) -> -
B20: 9 | J20: =I20*G20 -> 0
B21: 10 | J21: =I21*G21 -> 0
B22: 11 | J22: =I22*G22 -> 0
B23: 12 | J23: =I23*G23 -> 0
B24: 13 | J24: =I24*G24 -> 0
B25: 14 | J25: =I25*G25 -> 0
B26: 15 | J26: =I26*G26 -> 0
B27: 16 | J27: =I27*G27 -> 0
B28: 17 | J28: =I28*G28 -> 0
B29: 18 | J29: =I29*G29 -> 0
B30: 19 | J30: =I30*G30 -> 0
B31: 20 | J31: =I31*G31 -> 0
... B111: 100 | J111: =I111*G111 -> 0
